easycodeluna/__init__.py
easycodeluna/easycodeadvanced/__init__.py
easycodeluna/easycodeadvanced/lists.py
easycodeluna/easycodeadvanced/loops.py
easycodeluna/easycodebasics/__init__.py
easycodeluna/easycodebasics/conditionals.py
easycodeluna/easycodebasics/variables.py
easycodeluna-0.0.1.dist-info/METADATA
easycodeluna-0.0.1.dist-info/WHEEL
easycodeluna-0.0.1.dist-info/top_level.txt
easycodeluna-0.0.1.dist-info/RECORD
