Metadata-Version: 2.4
Name: easycodeluna
Version: 0.0.1
Summary: Pacote educativo com funções básicas de Python
Author: Aparecido Roberto Luna
License: MIT
Classifier: Programming Language :: Python :: 3
Classifier: License :: OSI Approved :: MIT License
Classifier: Intended Audience :: Education
Classifier: Topic :: Education
Requires-Python: >=3.6
Dynamic: author
Dynamic: classifier
Dynamic: description
Dynamic: description-content-type
Dynamic: license
Dynamic: requires-python
Dynamic: summary
